demos/__init__.py
demos/case1.py
demos/case2.py
wanyun_JitSdk/__init__.py
wanyun_JitSdk/common/__init__.py
wanyun_JitSdk/common/enums.py
wanyun_JitSdk/common/error.py
wanyun_JitSdk/core/__init__.py
wanyun_JitSdk/core/api.py
wanyun_JitSdk/core/request.py
wanyun_JitSdk/core/response.py
wanyun_JitSdk/core/sign.py
wanyun_jitsdk-1.0.7.dist-info/METADATA
wanyun_jitsdk-1.0.7.dist-info/WHEEL
wanyun_jitsdk-1.0.7.dist-info/top_level.txt
wanyun_jitsdk-1.0.7.dist-info/RECORD
