Metadata-Version: 2.4
Name: wanyun_JitSdk
Version: 1.0.7
Summary: Official Jit API Authorization SDK
Author: zangtao
Author-email: support@jit.pro
Keywords: python,jit,sdk,apiAuth
Classifier: Development Status :: 3 - Alpha
Classifier: Intended Audience :: Developers
Classifier: Programming Language :: Python :: 3
Classifier: Operating System :: MacOS :: MacOS X
Classifier: Operating System :: Microsoft :: Windows
Classifier: Operating System :: POSIX :: Linux
Requires-Dist: requests
Dynamic: author
Dynamic: author-email
Dynamic: classifier
Dynamic: description
Dynamic: description-content-type
Dynamic: keywords
Dynamic: requires-dist
Dynamic: summary
